{"schemaVersion":"DATA-R01-implementation-v1","batchId":"DATA-R01-IMPLEMENT-B11","sourceBatchId":"DATA-R01-VERIFY-B11","checkedAt":"2026-07-16","policy":{"acceptedVerificationStatuses":["verified","corrected"],"requireVariantConfirmed":true,"requireNonNullProposedValue":true,"unresolvedPolicy":"manualReview-only","sourceJoinPolicy":"sources-first","useCasePolicy":"merge-existing-candidate-never-blind-overwrite"},"targetRobotIds":["pal-talos","pal-kangaroo"],"robots":[{"robotId":"pal-talos","manufacturerId":"pal-robotics","identity":{"ready":true,"officialName":"TALOS","variant":"TALOS high-performance humanoid research platform","officialProductUrl":"https://pal-robotics.com/robot/talos/","checkedAt":"2026-07-16"},"positioningFacts":[{"value":"TALOS is positioned as an advanced humanoid robot designed to boost research","sourceUrl":"https://pal-robotics.com/robot/talos/"},{"value":"PAL describes TALOS as a walking biped for tasks in environments such as the Factory of the Future","sourceUrl":"https://pal-robotics.com/robot/talos/"},{"value":"TALOS is fully torque-controllable, configurable and developed in ROS","sourceUrl":"https://pal-robotics.com/robot/talos/"}],"robotPatch":{"specs":{"mobility":"biped","heightCm":175,"weightKg":95,"dof":32,"runtimeMin":90,"batteryCapacityWh":1080,"batterySystem":"lithium-ion battery","controlMethod":"joint-level torque control / ros_control / teleoperation options","sdk":"ROS / OROCOS / ros_control / MoveIt!","computePlatform":"2× Intel Core i7 PCs"},"clearSpecKeys":["speedMps","payloadKg"],"priceOffers":{"action":"clear","values":[]},"loadRatings":{"action":"replace","values":[{"scope":"single-arm","rating":"unspecified","kg":6,"condition":"6kg with each arm fully extended; official page does not label it rated or maximum","variant":"TALOS","sourceUrl":"https://pal-robotics.com/robot/talos/"}]},"usageExampleSourceUrls":{"action":"replace","values":["https://pal-robotics.com/blog/talos-research-torque-controlled-locomotion-for-humanoids-in-unknown-environments/","https://pal-robotics.com/blog/memmo-memories-robots-motion-generation/"]},"procurement":{"japanAvailability":"unknown"},"clearProcurementFields":[],"fieldEvidence":{"mobility":["https://pal-robotics.com/robot/talos/"],"heightCm":["https://pal-robotics.com/datasheet/talos/"],"weightKg":["https://pal-robotics.com/datasheet/talos/"],"dof":["https://pal-robotics.com/datasheet/talos/"],"runtimeMin":["https://pal-robotics.com/datasheet/talos/"],"batteryCapacityWh":["https://pal-robotics.com/datasheet/talos/"],"batterySystem":["https://pal-robotics.com/datasheet/talos/"],"controlMethod":["https://pal-robotics.com/robot/talos/"],"sdk":["https://pal-robotics.com/datasheet/talos/"],"computePlatform":["https://pal-robotics.com/datasheet/talos/"],"loadRatings":["https://pal-robotics.com/robot/talos/"]},"clearFieldEvidenceKeys":["speedMps","payloadKg","priceOffers"]},"currentDiff":{"specs":{"mobility":{"action":"unchanged","currentValue":"biped","proposedValue":"biped"},"heightCm":{"action":"unchanged","currentValue":175,"proposedValue":175},"weightKg":{"action":"unchanged","currentValue":95,"proposedValue":95},"speedMps":{"action":"remove","currentValue":0.83,"proposedValue":null},"dof":{"action":"unchanged","currentValue":32,"proposedValue":32},"payloadKg":{"action":"remove","currentValue":6,"proposedValue":null},"runtimeMin":{"action":"unchanged","currentValue":90,"proposedValue":90},"batteryCapacityWh":{"action":"add","currentValue":null,"proposedValue":1080},"chargeTimeMin":{"action":"unchanged","currentValue":null,"proposedValue":null},"batterySystem":{"action":"add","currentValue":null,"proposedValue":"lithium-ion battery"},"controlMethod":{"action":"add","currentValue":null,"proposedValue":"joint-level torque control / ros_control / teleoperation options"},"sdk":{"action":"add","currentValue":null,"proposedValue":"ROS / OROCOS / ros_control / MoveIt!"},"computePlatform":{"action":"add","currentValue":null,"proposedValue":"2× Intel Core i7 PCs"},"ipRating":{"action":"unchanged","currentValue":null,"proposedValue":null},"operatingTemperature":{"action":"unchanged","currentValue":null,"proposedValue":null},"safetyStandard":{"action":"unchanged","currentValue":null,"proposedValue":null}},"priceOffers":{"action":"clear","currentValue":null,"proposedValue":[]},"loadRatings":{"action":"replace","currentValue":null,"proposedValue":[{"scope":"single-arm","rating":"unspecified","kg":6,"condition":"6kg with each arm fully extended; official page does not label it rated or maximum","variant":"TALOS","sourceUrl":"https://pal-robotics.com/robot/talos/"}]},"usageExampleSourceUrls":{"action":"replace","currentValue":null,"proposedValue":["https://pal-robotics.com/blog/talos-research-torque-controlled-locomotion-for-humanoids-in-unknown-environments/","https://pal-robotics.com/blog/memmo-memories-robots-motion-generation/"]},"procurement":{"japanAvailability":{"action":"update","currentValue":"inquiry-required","proposedValue":"unknown"},"distributorJapan":{"action":"unchanged","currentValue":null,"proposedValue":null}}},"robotSourceRequirements":[{"url":"https://pal-robotics.com/robot/talos/","usedBy":["specs.mobility","specs.controlMethod","loadRatings"],"candidates":[{"kind":"official-product","checkedAt":"2026-07-16"},{"kind":"official-load-rating","checkedAt":"2026-07-16"}],"status":"existing","existingSource":{"title":"TALOS Humanoid Robot","url":"https://pal-robotics.com/robot/talos/","publisher":"PAL Robotics","checkedAt":"2026-05-30","reliability":"official"},"action":"refresh-checkedAt","proposedCheckedAt":"2026-07-16"},{"url":"https://pal-robotics.com/datasheet/talos/","usedBy":["specs.heightCm","specs.weightKg","specs.dof","specs.runtimeMin","specs.batteryCapacityWh","specs.batterySystem","specs.sdk","specs.computePlatform"],"candidates":[{"kind":"official-evidence","checkedAt":"2026-07-16"}],"status":"add-after-review","candidateSource":{"title":"TALOS official source","url":"https://pal-robotics.com/datasheet/talos/","publisher":"PAL Robotics","checkedAt":"2026-07-16","reliability":"official"},"reviewReason":"VERIFYで公式原典として採用済み。生成したtitle/publisherがページ実体に合うか確認する。"},{"url":"https://pal-robotics.com/blog/talos-research-torque-controlled-locomotion-for-humanoids-in-unknown-environments/","usedBy":["usageExampleSourceUrls"],"candidates":[{"kind":"usage-example","title":"TALOS research: torque-controlled locomotion for humanoids in unknown environments","publisher":"PAL Robotics","publishedAt":"2023-12-30","checkedAt":"2026-07-16"}],"status":"add-after-review","candidateSource":{"title":"TALOS research: torque-controlled locomotion for humanoids in unknown environments","url":"https://pal-robotics.com/blog/talos-research-torque-controlled-locomotion-for-humanoids-in-unknown-environments/","publisher":"PAL Robotics","publishedAt":"2023-12-30","checkedAt":"2026-07-16","reliability":"reported"},"reviewReason":"活用事例の媒体種別に応じてofficial/reportedを最終確認する。"},{"url":"https://pal-robotics.com/blog/memmo-memories-robots-motion-generation/","usedBy":["usageExampleSourceUrls"],"candidates":[{"kind":"usage-example","title":"MEMMO: Giving memories to robots for a better motion generation","publisher":"PAL Robotics","publishedAt":"2019-02-01","checkedAt":"2026-07-16"}],"status":"add-after-review","candidateSource":{"title":"MEMMO: Giving memories to robots for a better motion generation","url":"https://pal-robotics.com/blog/memmo-memories-robots-motion-generation/","publisher":"PAL Robotics","publishedAt":"2019-02-01","checkedAt":"2026-07-16","reliability":"reported"},"reviewReason":"活用事例の媒体種別に応じてofficial/reportedを最終確認する。"},{"url":"https://pal-robotics.com/contact/","usedBy":["procurement.japanAvailability"],"candidates":[{"kind":"official-procurement","checkedAt":"2026-07-16"}],"status":"add-after-review","candidateSource":{"title":"TALOS official source","url":"https://pal-robotics.com/contact/","publisher":"PAL Robotics","checkedAt":"2026-07-16","reliability":"official"},"reviewReason":"VERIFYで公式原典として採用済み。生成したtitle/publisherがページ実体に合うか確認する。"},{"url":"https://pal-robotics.com/about-us/","usedBy":["procurement.distributorJapan"],"candidates":[{"kind":"official-procurement","checkedAt":"2026-07-16"}],"status":"add-after-review","candidateSource":{"title":"TALOS official source","url":"https://pal-robotics.com/about-us/","publisher":"PAL Robotics","checkedAt":"2026-07-16","reliability":"official"},"reviewReason":"VERIFYで公式原典として採用済み。生成したtitle/publisherがページ実体に合うか確認する。"}],"useCaseRelations":[{"useCaseId":"research-development","evidenceSourceUrl":"https://pal-robotics.com/robot/talos/","officialExpression":"advanced humanoid robot designed to boost your research","proposedRelation":{"robotId":"pal-talos","fit":"possible","basis":"official-use-case","evidenceSourceUrls":["https://pal-robotics.com/robot/talos/"],"reason":"公式ページで研究向けプラットフォームとして明示されている。ただし特定研究機関への導入事例は現行確認できていない。"},"action":"unchanged","currentRelation":{"robotId":"pal-talos","fit":"possible","basis":"official-use-case","evidenceSourceUrls":["https://pal-robotics.com/robot/talos/"],"reason":"公式ページで研究向けプラットフォームとして明示されている。ただし特定研究機関への導入事例は現行確認できていない。"},"checkedAt":"2026-07-16"},{"useCaseId":"factory-assembly-support","evidenceSourceUrl":"https://pal-robotics.com/blog/memmo-memories-robots-motion-generation/","officialExpression":"Factory of the Future / aircraft manufacturing industry / industrial complex tasks","proposedRelation":{"robotId":"pal-talos","fit":"possible","basis":"official-use-case","evidenceSourceUrls":["https://pal-robotics.com/blog/memmo-memories-robots-motion-generation/"],"reason":"Factory of the Future / aircraft manufacturing industry / industrial complex tasks（公式情報で確認）"},"action":"add","currentRelation":null,"checkedAt":"2026-07-16"}],"useCaseSourceRequirements":[{"useCaseId":"research-development","url":"https://pal-robotics.com/robot/talos/","status":"existing","existingSource":{"title":"TALOS – PAL Robotics","url":"https://pal-robotics.com/robot/talos/","publisher":"PAL Robotics","checkedAt":"2026-06-28","reliability":"official","note":"TALOS が研究向けプラットフォームとして明示されている公式根拠。Waterloo RoboHub導入はこの出典だけでは確認できないため、deployment根拠から外した。"},"action":"refresh-checkedAt","proposedCheckedAt":"2026-07-16"},{"useCaseId":"factory-assembly-support","url":"https://pal-robotics.com/blog/memmo-memories-robots-motion-generation/","status":"add-after-review","candidateSource":{"title":"TALOS official use case","url":"https://pal-robotics.com/blog/memmo-memories-robots-motion-generation/","publisher":"PAL Robotics","checkedAt":"2026-07-16","reliability":"official"},"reviewReason":"生成した説明用titleとpublisherを人間が確認する。"}],"manualReview":{"unresolvedFields":[],"unresolvedPriceOffers":[],"unresolvedLoadRatings":[],"unresolvedUsageExamples":[],"unresolvedOfficialUseCases":[],"useCaseGaps":[],"rejectedUsageExamples":[],"procurementCandidates":[],"unresolvedProcurement":[{"field":"procurementModels","rawValue":["purchase","inquiry","research-partnership"],"sourceUrls":["https://pal-robotics.com/robot/talos/","https://pal-robotics.com/contact/","https://pal-robotics.com/about-us/"],"reason":"既存enumでは意味を保持できないraw値があり、推測変換しない。","currentValue":["purchase","inquiry"]},{"field":"marketAvailability","rawValue":{"status":"needs-review","rawValue":"PAL presents TALOS as a configurable research/industrial platform with Request a quote; current production stock and standard shipment terms are not published","sourceUrl":"https://pal-robotics.com/robot/talos/","evidenceSummary":"公式購入相談はあるが、現行在庫・標準納期は非公開。"},"sourceUrls":["https://pal-robotics.com/robot/talos/"],"reason":"既存enumでは意味を保持できないため推測変換しない。","currentValue":null},{"field":"supportNote","rawValue":{"status":"needs-review","rawValue":"Official contact, software documentation and research partnership route are public; Japan support, repair SLA and field-service terms are not published","sourceUrl":"https://pal-robotics.com/robot/talos/","evidenceSummary":"技術・問い合わせ導線はあるが国内サポート条件は非公開。"},"sourceUrls":["https://pal-robotics.com/robot/talos/"],"reason":"公式ページを再確認したが、conflict/variantまたは取得状態を解消できない。","currentValue":null}],"conflicts":["TALOSの荷重表現は腕scopeのみで、scalar payloadKgへ移していない。","TALOSの稼働時間はwalking 1.5hとstand-by 3hで条件が異なる。"],"humanReviewRequired":["TALOSの日本向け販売・保守窓口と最新見積条件を公式窓口で確認する。"]},"applyGate":{"identityReady":true,"missingRobotSourceCount":5,"missingUseCaseSourceCount":1,"sourceMetadataReviewRequired":true,"hasUnresolvedCurrentSpecValues":false},"cardCoverageFromVerifiedResearch":{"officialUseCase":true,"size":true,"publicPrice":false,"runtime":true}},{"robotId":"pal-kangaroo","manufacturerId":"pal-robotics","identity":{"ready":true,"officialName":"KANGAROO","variant":"KANGAROO modular biped humanoid research platform; 4/5/7 DoF arm and end-effector configurations","officialProductUrl":"https://pal-robotics.com/robot/kangaroo/","checkedAt":"2026-07-16"},"positioningFacts":[{"value":"KANGAROO is positioned as a development-ready humanoid for dynamic locomotion, reinforcement learning and embodied AI research","sourceUrl":"https://pal-robotics.com/robot/kangaroo/"},{"value":"PAL describes KANGAROO as a modular biped platform with configurable arm and end-effector options","sourceUrl":"https://pal-robotics.com/robot/kangaroo/"},{"value":"PAL timeline states KANGAROO became ready for sale with two versions, KANGAROO and KANGAROO PRO","sourceUrl":"https://pal-robotics.com/timeline/"}],"robotPatch":{"specs":{"mobility":"biped","heightCm":158,"speedMps":2,"runtimeMin":180,"controlMethod":"ros2_control / configurable actuator modes / VR teleoperation","sdk":"ROS 2 / ros2_control / PAL OS / C++ and Python API","computePlatform":"2× Intel i7 PCs; optional NVIDIA Jetson GPU","safetyStandard":"IEC 61508 SIL 2 / EN ISO 13849-1 PL d"},"clearSpecKeys":[],"priceOffers":{"action":"clear","values":[]},"loadRatings":{"action":"replace","values":[{"scope":"single-arm","rating":"unspecified","kg":7,"condition":"4 DoF arm, arm fully extended; official table does not label rated/maximum","variant":"KANGAROO 4 DoF arms","sourceUrl":"https://pal-robotics.com/datasheet/kangaroo/"},{"scope":"dual-arm","rating":"unspecified","kg":30,"condition":"4 DoF arms, bi-manual manipulation; official table does not label rated/maximum","variant":"KANGAROO 4 DoF arms","sourceUrl":"https://pal-robotics.com/datasheet/kangaroo/"},{"scope":"single-arm","rating":"unspecified","kg":5,"condition":"5 DoF arm, arm fully extended; official table does not label rated/maximum","variant":"KANGAROO 5 DoF arms","sourceUrl":"https://pal-robotics.com/datasheet/kangaroo/"},{"scope":"dual-arm","rating":"unspecified","kg":28,"condition":"5 DoF arms, bi-manual manipulation; official table does not label rated/maximum","variant":"KANGAROO 5 DoF arms","sourceUrl":"https://pal-robotics.com/datasheet/kangaroo/"},{"scope":"single-arm","rating":"unspecified","kg":3,"condition":"7 DoF arm, arm fully extended; official table does not label rated/maximum","variant":"KANGAROO 7 DoF arms","sourceUrl":"https://pal-robotics.com/datasheet/kangaroo/"},{"scope":"dual-arm","rating":"unspecified","kg":25,"condition":"7 DoF arms, bi-manual manipulation; official table does not label rated/maximum","variant":"KANGAROO 7 DoF arms","sourceUrl":"https://pal-robotics.com/datasheet/kangaroo/"}]},"usageExampleSourceUrls":{"action":"replace","values":["https://pal-robotics.com/blog/kangaroo-biped-research-platform-updates/"]},"procurement":{"japanAvailability":"unknown"},"clearProcurementFields":[],"fieldEvidence":{"mobility":["https://pal-robotics.com/robot/kangaroo/"],"heightCm":["https://pal-robotics.com/robot/kangaroo/"],"speedMps":["https://pal-robotics.com/datasheet/kangaroo/"],"runtimeMin":["https://pal-robotics.com/datasheet/kangaroo/"],"controlMethod":["https://pal-robotics.com/robot/kangaroo/"],"sdk":["https://pal-robotics.com/robot/kangaroo/"],"computePlatform":["https://pal-robotics.com/datasheet/kangaroo/"],"safetyStandard":["https://pal-robotics.com/datasheet/kangaroo/"],"loadRatings":["https://pal-robotics.com/datasheet/kangaroo/"]},"clearFieldEvidenceKeys":["priceOffers"]},"currentDiff":{"specs":{"mobility":{"action":"unchanged","currentValue":"biped","proposedValue":"biped"},"heightCm":{"action":"update","currentValue":160,"proposedValue":158},"speedMps":{"action":"update","currentValue":1.25,"proposedValue":2},"payloadKg":{"action":"unchanged","currentValue":null,"proposedValue":null},"runtimeMin":{"action":"update","currentValue":240,"proposedValue":180},"chargeTimeMin":{"action":"unchanged","currentValue":null,"proposedValue":null},"controlMethod":{"action":"add","currentValue":null,"proposedValue":"ros2_control / configurable actuator modes / VR teleoperation"},"sdk":{"action":"add","currentValue":null,"proposedValue":"ROS 2 / ros2_control / PAL OS / C++ and Python API"},"computePlatform":{"action":"add","currentValue":null,"proposedValue":"2× Intel i7 PCs; optional NVIDIA Jetson GPU"},"ipRating":{"action":"unchanged","currentValue":null,"proposedValue":null},"operatingTemperature":{"action":"unchanged","currentValue":null,"proposedValue":null},"safetyStandard":{"action":"add","currentValue":null,"proposedValue":"IEC 61508 SIL 2 / EN ISO 13849-1 PL d"}},"priceOffers":{"action":"clear","currentValue":null,"proposedValue":[]},"loadRatings":{"action":"replace","currentValue":null,"proposedValue":[{"scope":"single-arm","rating":"unspecified","kg":7,"condition":"4 DoF arm, arm fully extended; official table does not label rated/maximum","variant":"KANGAROO 4 DoF arms","sourceUrl":"https://pal-robotics.com/datasheet/kangaroo/"},{"scope":"dual-arm","rating":"unspecified","kg":30,"condition":"4 DoF arms, bi-manual manipulation; official table does not label rated/maximum","variant":"KANGAROO 4 DoF arms","sourceUrl":"https://pal-robotics.com/datasheet/kangaroo/"},{"scope":"single-arm","rating":"unspecified","kg":5,"condition":"5 DoF arm, arm fully extended; official table does not label rated/maximum","variant":"KANGAROO 5 DoF arms","sourceUrl":"https://pal-robotics.com/datasheet/kangaroo/"},{"scope":"dual-arm","rating":"unspecified","kg":28,"condition":"5 DoF arms, bi-manual manipulation; official table does not label rated/maximum","variant":"KANGAROO 5 DoF arms","sourceUrl":"https://pal-robotics.com/datasheet/kangaroo/"},{"scope":"single-arm","rating":"unspecified","kg":3,"condition":"7 DoF arm, arm fully extended; official table does not label rated/maximum","variant":"KANGAROO 7 DoF arms","sourceUrl":"https://pal-robotics.com/datasheet/kangaroo/"},{"scope":"dual-arm","rating":"unspecified","kg":25,"condition":"7 DoF arms, bi-manual manipulation; official table does not label rated/maximum","variant":"KANGAROO 7 DoF arms","sourceUrl":"https://pal-robotics.com/datasheet/kangaroo/"}]},"usageExampleSourceUrls":{"action":"replace","currentValue":null,"proposedValue":["https://pal-robotics.com/blog/kangaroo-biped-research-platform-updates/"]},"procurement":{"japanAvailability":{"action":"update","currentValue":"inquiry-required","proposedValue":"unknown"},"distributorJapan":{"action":"unchanged","currentValue":null,"proposedValue":null}}},"robotSourceRequirements":[{"url":"https://pal-robotics.com/robot/kangaroo/","usedBy":["specs.mobility","specs.heightCm","specs.controlMethod","specs.sdk"],"candidates":[{"kind":"official-product","checkedAt":"2026-07-16"}],"status":"existing","existingSource":{"title":"Kangaroo","url":"https://pal-robotics.com/robot/kangaroo/","publisher":"PAL Robotics","checkedAt":"2026-05-30","reliability":"official"},"action":"refresh-checkedAt","proposedCheckedAt":"2026-07-16"},{"url":"https://pal-robotics.com/datasheet/kangaroo/","usedBy":["specs.speedMps","specs.runtimeMin","specs.computePlatform","specs.safetyStandard","loadRatings","procurement.supportNote"],"candidates":[{"kind":"official-evidence","checkedAt":"2026-07-16"},{"kind":"official-load-rating","checkedAt":"2026-07-16"},{"kind":"official-procurement","checkedAt":"2026-07-16"}],"status":"add-after-review","candidateSource":{"title":"KANGAROO official source","url":"https://pal-robotics.com/datasheet/kangaroo/","publisher":"PAL Robotics","checkedAt":"2026-07-16","reliability":"official"},"reviewReason":"VERIFYで公式原典として採用済み。生成したtitle/publisherがページ実体に合うか確認する。"},{"url":"https://pal-robotics.com/blog/kangaroo-biped-research-platform-updates/","usedBy":["usageExampleSourceUrls"],"candidates":[{"kind":"usage-example","title":"Kangaroo: The dynamic robot & the latest developments","publisher":"PAL Robotics","publishedAt":"2022-05-31","checkedAt":"2026-07-16"}],"status":"add-after-review","candidateSource":{"title":"Kangaroo: The dynamic robot & the latest developments","url":"https://pal-robotics.com/blog/kangaroo-biped-research-platform-updates/","publisher":"PAL Robotics","publishedAt":"2022-05-31","checkedAt":"2026-07-16","reliability":"reported"},"reviewReason":"活用事例の媒体種別に応じてofficial/reportedを最終確認する。"},{"url":"https://pal-robotics.com/contact/","usedBy":["procurement.japanAvailability"],"candidates":[{"kind":"official-procurement","checkedAt":"2026-07-16"}],"status":"add-after-review","candidateSource":{"title":"KANGAROO official source","url":"https://pal-robotics.com/contact/","publisher":"PAL Robotics","checkedAt":"2026-07-16","reliability":"official"},"reviewReason":"VERIFYで公式原典として採用済み。生成したtitle/publisherがページ実体に合うか確認する。"},{"url":"https://pal-robotics.com/about-us/","usedBy":["procurement.distributorJapan"],"candidates":[{"kind":"official-procurement","checkedAt":"2026-07-16"}],"status":"add-after-review","candidateSource":{"title":"KANGAROO official source","url":"https://pal-robotics.com/about-us/","publisher":"PAL Robotics","checkedAt":"2026-07-16","reliability":"official"},"reviewReason":"VERIFYで公式原典として採用済み。生成したtitle/publisherがページ実体に合うか確認する。"}],"useCaseRelations":[{"useCaseId":"research-development","evidenceSourceUrl":"https://pal-robotics.com/robot/kangaroo/","officialExpression":"dynamic locomotion research / development-ready humanoid","proposedRelation":{"robotId":"pal-kangaroo","fit":"possible","basis":"official-use-case","evidenceSourceUrls":["https://pal-robotics.com/robot/kangaroo/"],"reason":"dynamic locomotion research / development-ready humanoid（公式情報で確認）"},"action":"add","currentRelation":null,"checkedAt":"2026-07-16"},{"useCaseId":"research-ai-simulation","evidenceSourceUrl":"https://pal-robotics.com/robot/kangaroo/","officialExpression":"reinforcement learning and embodied AI; MuJoCo/mjlab and RL tools","proposedRelation":{"robotId":"pal-kangaroo","fit":"possible","basis":"official-use-case","evidenceSourceUrls":["https://pal-robotics.com/robot/kangaroo/"],"reason":"reinforcement learning and embodied AI; MuJoCo/mjlab and RL tools（公式情報で確認）"},"action":"add","currentRelation":null,"checkedAt":"2026-07-16"},{"useCaseId":"research-prototype-dev","evidenceSourceUrl":"https://pal-robotics.com/robot/kangaroo/","officialExpression":"customize KANGAROO to foster breakthroughs in robot learning and robotic movement","proposedRelation":{"robotId":"pal-kangaroo","fit":"possible","basis":"official-use-case","evidenceSourceUrls":["https://pal-robotics.com/robot/kangaroo/"],"reason":"customize KANGAROO to foster breakthroughs in robot learning and robotic movement（公式情報で確認）"},"action":"add","currentRelation":null,"checkedAt":"2026-07-16"}],"useCaseSourceRequirements":[{"useCaseId":"research-development","url":"https://pal-robotics.com/robot/kangaroo/","status":"add-after-review","candidateSource":{"title":"KANGAROO official use case","url":"https://pal-robotics.com/robot/kangaroo/","publisher":"PAL Robotics","checkedAt":"2026-07-16","reliability":"official"},"reviewReason":"生成した説明用titleとpublisherを人間が確認する。"},{"useCaseId":"research-ai-simulation","url":"https://pal-robotics.com/robot/kangaroo/","status":"add-after-review","candidateSource":{"title":"KANGAROO official use case","url":"https://pal-robotics.com/robot/kangaroo/","publisher":"PAL Robotics","checkedAt":"2026-07-16","reliability":"official"},"reviewReason":"生成した説明用titleとpublisherを人間が確認する。"},{"useCaseId":"research-prototype-dev","url":"https://pal-robotics.com/robot/kangaroo/","status":"add-after-review","candidateSource":{"title":"KANGAROO official use case","url":"https://pal-robotics.com/robot/kangaroo/","publisher":"PAL Robotics","checkedAt":"2026-07-16","reliability":"official"},"reviewReason":"生成した説明用titleとpublisherを人間が確認する。"}],"manualReview":{"unresolvedFields":[{"field":"weightKg","rawStatus":"needs-review","rawValue":"50–65kg","sourceUrl":"https://pal-robotics.com/robot/kangaroo/","reason":"今回、公式ページを開いたが、rawのneeds-review/conflict（variant、単位、意味または公式情報間の競合）が残るため採用しない。","currentValue":38,"currentValueRequiresReview":true},{"field":"dof","rawStatus":"needs-review","rawValue":"Total DoF 14–40 platform configuration; single arm 4, 5 or 7 DoF; torso 2 DoF; single leg 6 DoF","sourceUrl":"https://pal-robotics.com/robot/kangaroo/","reason":"今回、公式ページを開いたが、rawのneeds-review/conflict（variant、単位、意味または公式情報間の競合）が残るため採用しない。","currentValue":28,"currentValueRequiresReview":true},{"field":"batteryCapacityWh","rawStatus":"needs-review","rawValue":"Official page/datasheet state Battery 976 Ah / 15 Ah wording; no voltage-based Wh value and unit consistency requires confirmation","sourceUrl":"https://pal-robotics.com/datasheet/kangaroo/","reason":"今回、公式ページを開いたが、rawのneeds-review/conflict（variant、単位、意味または公式情報間の競合）が残るため採用しない。","currentValue":null,"currentValueRequiresReview":false},{"field":"batterySystem","rawStatus":"needs-review","rawValue":"Battery is listed with a 976 Ah / 15 Ah value, but chemistry, voltage and configuration-specific interpretation are not clear","sourceUrl":"https://pal-robotics.com/datasheet/kangaroo/","reason":"今回、公式ページを開いたが、rawのneeds-review/conflict（variant、単位、意味または公式情報間の競合）が残るため採用しない。","currentValue":null,"currentValueRequiresReview":false}],"unresolvedPriceOffers":[],"unresolvedLoadRatings":[],"unresolvedUsageExamples":[],"unresolvedOfficialUseCases":[],"useCaseGaps":[],"rejectedUsageExamples":[],"procurementCandidates":[{"field":"supportNote","candidate":{"status":"found","rawValue":"Official datasheet lists remote diagnostics/support, onsite installation and training, hardware maintenance/replacement, warranty extension and software upgrades","sourceUrl":"https://pal-robotics.com/datasheet/kangaroo/","evidenceSummary":"公式PDFにサポートサービス項目。日本固有条件は非公開。"},"sourceUrls":["https://pal-robotics.com/datasheet/kangaroo/"],"reason":"現行Robot fieldへ意味を失わず直接投影できないため、人間が短い表示値へ編集する。"}],"unresolvedProcurement":[{"field":"procurementModels","rawValue":["purchase","inquiry","research-partnership"],"sourceUrls":["https://pal-robotics.com/robot/kangaroo/","https://pal-robotics.com/timeline/","https://pal-robotics.com/contact/","https://pal-robotics.com/about-us/","https://pal-robotics.com/datasheet/kangaroo/"],"reason":"既存enumでは意味を保持できないraw値があり、推測変換しない。","currentValue":["purchase","inquiry"]},{"field":"marketAvailability","rawValue":{"status":"needs-review","rawValue":"PAL timeline says KANGAROO and KANGAROO PRO became ready for sale; current product page uses Request a quote and does not publish stock or shipment terms","sourceUrl":"https://pal-robotics.com/timeline/","evidenceSummary":"公式timelineのready for saleは確認したが、現在の在庫・納期は非公開。"},"sourceUrls":["https://pal-robotics.com/timeline/"],"reason":"既存enumでは意味を保持できないため推測変換しない。","currentValue":null}],"conflicts":["KANGAROOの身長・重量・DoF・荷重はplatform configuration依存で、単一値に統合していない。","公式電池表記は976 Ah / 15 Ahと読み取れるが、電圧・Wh・variant対応がなく容量と方式をneeds-reviewにした。"],"humanReviewRequired":["KANGAROOの代表arm configuration（4/5/7 DoF）を公開Robotレコードで決定する。","公式電池datasheetの976 Ah / 15 Ah表記と単位をPAL Roboticsへ確認する。","日本向け販売・保守窓口と最新見積条件を公式窓口で確認する。"]},"applyGate":{"identityReady":true,"missingRobotSourceCount":4,"missingUseCaseSourceCount":3,"sourceMetadataReviewRequired":true,"hasUnresolvedCurrentSpecValues":true},"cardCoverageFromVerifiedResearch":{"officialUseCase":true,"size":true,"publicPrice":false,"runtime":true}}],"counts":{"specsToSet":18,"specsToClear":2,"priceOffers":0,"loadRatings":7,"usageExamples":3,"officialUseCases":5,"useCaseRelationReviews":0,"useCaseGaps":0,"unresolved":9,"missingRobotSources":9,"missingUseCaseSources":4}}
